{
    "version": "0.8",
    "metrics_params": {
        "aoi_units": "hours",
        "overlap_window_s": 3600,
        "overlap_count_option": "single_overlap",
        "window_overlap_option": "mutex_window",
        "overlap_include_dlnks": false,
        "overlap_remove_same_obs": true
    },
    "route_selection_general_params": {
        "plot_route_selection_results":       false,
        "adjust_window_timing_post_selection": true,
        "min_rs_route_dv_Mb" :  50, 
        "run_rs_parallel" :  true, 
        "num_parallel_workers" :  8,
        "include_crosslinks" :  true,
        "_comments": [
            "min_rs_route_dv_Mb: this is the minimum obs dv in megabits that a simple DataRoute object must deliver in order for it to not be ignored"
        ]
    },
    "route_selection_params_v1": {
        "num_paths" :  5,
        "solver_max_runtime_s" :  30,
        "solver_name" :  "gurobi",
        "solver_run_remotely" :   false
    },
    "route_selection_params_v2": {
        "verbose_step1" :  true,
        "step2_params": {
            "num_rts_sel_per_obs_overlap": 30,
            "num_rts_sel_per_obs_dv": 6,
            "num_rts_sel_per_obs_lat": 6
        }
    },
    "route_selection_params_v3": {
        "verbose_step1" :  true,
        "step1_params": {
            "num_routes_to_pick": 1
        },
        "step2_params": {
            "num_rts_sel_per_obs_overlap": 30,
            "num_rts_sel_per_obs_dv": 6,
            "num_rts_sel_per_obs_lat": 6
        }
    },
    "activity_scheduling_params": {
        "_comments": [
            "min_obs_dv_dlnk_req_Mb: this is the minimum obs dv in megabits that must be downlinked for an obs (data route/obs dlnk) in order for it to count it towards objective terms like route latency, number of routes. Also used in local planner to count unified flows",
            "min_latency_for_sf_1_mins: this is the mimimum latency requirement for the highest latency score factor, 1.0. If multiple routes/dlnks for a single obs have latency less than this, they will both have sf 1.0"
        ],
        "min_obs_dv_dlnk_req_Mb" :  100,
        "min_latency_for_sf_1_mins" :  10,
        "dv_epsilon_Mb" :  1,
        "fixed_utilization_epsilon" :  0.00001,
        "solver_name" :  "gurobi",
        "solver_params": {
            "run_remotely" :   false,
            "max_runtime_s" : 1000,
            "optimality_gap" :  1e-2,
            "integer_feasibility_tolerance" :  1e-5,
            "gurobi": {
                "_helpful_links": [
                    "http://www.gurobi.com/documentation/7.5/refman/intfeastol.html#parameter:IntFeasTol",
                    "http://www.gurobi.com/documentation/7.5/refman/mipgap2.html#parameter:MIPGap",
                    "http://www.gurobi.com/documentation/7.5/refman/timelimit.html#parameter:TimeLimit"
                ]
            },
            "cplex": {
                "_helpful_links": [
                    "https://www.ibm.com/support/knowledgecenter/SSSA5P_12.8.0/ilog.odms.cplex.help/CPLEX/Parameters/topics/introListAlpha.html"
                ]
            }
        },
        "obj_weights": {
            "obs_dv": 1.0,
            "route_latency": 1.0,
            "energy_storage": 1.0,
            "existing_routes": 1.0,
            "inter_sat_act_constr_violations": 100.0,
            "intra_sat_act_constr_violations": 100.0
        },
        "resource_delta_t_s": 10,
        "enforce_data_storage_constr": true,
        "enforce_energy_storage_constr": true,
        "resource_margin_obj_num_timepoints": 30,
        "run_activity_scheduling":  true,
        "run_coupled_rs_as": false
    },
    "pickle_params":  {
        "pickle_route_selection_step1_results":                   false,
        "pickle_route_selection_step2_results":                   false,
        "pickle_act_scheduling_results":                            false
    },
    "other_params": {
        "targ_id_ignore_list": [],
        "gs_id_ignore_list": [],
        "min_allowed_dv_xlnk_Mb" : 100,
        "min_allowed_dv_dlnk_Mb" : 100,
        "latency_calculation": {
            "dlnk": "center",
            "obs": "center"
        },
        "load_windows_from_file":    true,
        "_comment": "the below switches whether or not xlnk windows are separated out for each crosslink access, into a pair of windows with one sat transmitting in one window, and the other transmitting in the other. Enable to allow both satellites to be sharing a single, unified window, with each using xlnk-tx power setting (removes a bit of RAM/computation overhead, doesn't seem like a big help in practice because route selection cuts down the choices so well)",
        "use_symmetric_xlnk_windows": false
    },
    "plot_params":  {
        "plot_RS_include_obs_labels": true,
        "plot_RS_include_dlnk_labels": true,
        "plot_RS_include_xlnk_labels": true,
        "plot_AS_include_obs_labels": true,
        "plot_AS_include_dlnk_labels": true,
        "plot_AS_include_xlnk_labels": true,
        "plot_fig_extension":  "pdf",
        "time_units":  "minutes",
        "winds_plot_obs":  true,
        "winds_plot_obs_choices":  true,
        "winds_plot_dlnks":  true,
        "winds_plot_dlnks_choices":   true,
        "winds_plot_xlnks":  true,
        "winds_plot_xlnks_choices":    true,
        "energy_usage_plot_params": {
            "plot_bound_e_min_Wh_delta": -1,    
            "plot_bound_e_max_Wh_delta": 1,
            "show_min_max_bounds": true,
            "include_eclipse_windows": true
        },
        "data_usage_plot_params": {
            "plot_bound_d_min_Gb_delta": -1,    
            "plot_bound_d_max_Gb_delta": 1,
            "show_min_max_bounds": true,
            "include_eclipse_windows": true
        },
        "obs_aoi_metrics_plot_params" : {
            "plot_bound_min_aoi_hours": 0,    
            "plot_bound_max_aoi_hours": 4
        },
        "cmd_aoi_metrics_plot_params" : {
            "plot_bound_min_aoi_hours": 0,    
            "plot_bound_max_aoi_hours": 1.5
        },
        "tlm_aoi_metrics_plot_params" : {
            "plot_bound_min_aoi_hours": 0,    
            "plot_bound_max_aoi_hours": 1.5
        }
    }
}
